distributions/Binomialdistribution.py
distributions/Gaussiandistribution.py
distributions/Generaldistribution.py
distributions/Simple.py
distributions/SimpleSpark.py
distributions/__init__.py
epidistributions-0.1.dist-info/METADATA
epidistributions-0.1.dist-info/WHEEL
epidistributions-0.1.dist-info/top_level.txt
epidistributions-0.1.dist-info/RECORD
