Metadata-Version: 2.1
Name: epidistributions
Version: 0.1
Summary: Gaussian distributions
Home-page: UNKNOWN
Author: David Tan
Author-email: UNKNOWN
License: UNKNOWN
Platform: UNKNOWN
